pf_simulation_modeler/__init__.py
pf_simulation_modeler/app/__init__.py
pf_simulation_modeler/app/__main__.py
pf_simulation_modeler/app/jupyter.py
pf_simulation_modeler/app/engine/__init__.py
pf_simulation_modeler/app/engine/boundary_conditions.py
pf_simulation_modeler/app/engine/cli.py
pf_simulation_modeler/app/engine/domain.py
pf_simulation_modeler/app/engine/engine.py
pf_simulation_modeler/app/engine/files.py
pf_simulation_modeler/app/engine/pressure.py
pf_simulation_modeler/app/engine/save_project.py
pf_simulation_modeler/app/engine/solver.py
pf_simulation_modeler/app/engine/timing.py
pf_simulation_modeler/app/engine/model/boundary.yaml
pf_simulation_modeler/app/engine/model/boundary_ui.xml
pf_simulation_modeler/app/engine/model/cycle.yaml
pf_simulation_modeler/app/engine/model/cycle_ui.xml
pf_simulation_modeler/app/engine/model/domain.yaml
pf_simulation_modeler/app/engine/model/domain_ui.xml
pf_simulation_modeler/app/engine/model/output_readme.md
pf_simulation_modeler/app/engine/model/soil.yaml
pf_simulation_modeler/app/engine/model/soil_ui.xml
pf_simulation_modeler/app/engine/model/solver.yaml
pf_simulation_modeler/app/engine/model/solver_ui.xml
pf_simulation_modeler/app/engine/model/timing.yaml
pf_simulation_modeler/app/engine/snippets/__init__.py
pf_simulation_modeler/app/engine/snippets/boundary_conditions.py
pf_simulation_modeler/app/engine/snippets/domain.py
pf_simulation_modeler/app/engine/snippets/domain_builder.py
pf_simulation_modeler/app/engine/snippets/snippet_manager.py
pf_simulation_modeler/app/engine/snippets/solver.py
pf_simulation_modeler/app/engine/snippets/subsurface_properties.py
pf_simulation_modeler/app/engine/snippets/timing.py
pf_simulation_modeler/app/ui/__init__.py
pf_simulation_modeler/app/ui/boundary_conditions.py
pf_simulation_modeler/app/ui/code_gen.py
pf_simulation_modeler/app/ui/domain.py
pf_simulation_modeler/app/ui/file_db.py
pf_simulation_modeler/app/ui/pressure.py
pf_simulation_modeler/app/ui/save_project.py
pf_simulation_modeler-0.1.1.dist-info/LICENSE
pf_simulation_modeler-0.1.1.dist-info/METADATA
pf_simulation_modeler-0.1.1.dist-info/WHEEL
pf_simulation_modeler-0.1.1.dist-info/entry_points.txt
pf_simulation_modeler-0.1.1.dist-info/top_level.txt
pf_simulation_modeler-0.1.1.dist-info/RECORD
